cppython_pdm/__init__.py
cppython_pdm/plugin.py
cppython_pdm-0.3.0.dist-info/entry_points.txt
cppython_pdm-0.3.0.dist-info/WHEEL
cppython_pdm-0.3.0.dist-info/METADATA
cppython_pdm-0.3.0.dist-info/license_files/LICENSE.md
cppython_pdm-0.3.0.dist-info/RECORD
