Metadata-Version: 2.1
Name: cppython-pdm
Version: 0.3.0
Summary: Interface plugin for CPPython that hooks into PDM
License: MIT
Author-email: Synodic Software <contact@synodic.software>
Requires-Python: >=3.10
Requires-Dist: cppython>=0.6.1.dev4
Requires-Dist: pdm>=1.14.1
Project-URL: homepage, https://github.com/Synodic-Software/CPPython-PDM
Project-URL: repository, https://github.com/Synodic-Software/CPPython-PDM
